adapter_plus/__init__.py
adapter_plus/vit_adapter.py
adapter_plus-0.1.0.dist-info/LICENSE
adapter_plus-0.1.0.dist-info/METADATA
adapter_plus-0.1.0.dist-info/WHEEL
adapter_plus-0.1.0.dist-info/RECORD
