Metadata-Version: 2.1
Name: adapter-plus
Version: 0.1.0
Summary: Adapter+ implementation for vision transformer backbones from timm
Home-page: https://github.com/visinf/adapter_plus
License: Apache-2.0
Author: Jan-Martin Steitz
Author-email: jan-martin.steitz@visinf.tu-darmstadt.de
Requires-Python: >=3.9
Classifier: Intended Audience :: Science/Research
Classifier: License :: OSI Approved :: Apache Software License
Classifier: Programming Language :: Python :: 3
Classifier: Programming Language :: Python :: 3.9
Classifier: Programming Language :: Python :: 3.10
Classifier: Programming Language :: Python :: 3.11
Classifier: Programming Language :: Python :: 3.12
Classifier: Topic :: Scientific/Engineering :: Artificial Intelligence
Classifier: Topic :: Software Development :: Libraries :: Python Modules
Requires-Dist: omegaconf (>=2.3)
Requires-Dist: timm (>=0.9)
Project-URL: Repository, https://github.com/visinf/adapter_plus
